setup.py
FormalMethodsVLSI.egg-info/PKG-INFO
FormalMethodsVLSI.egg-info/SOURCES.txt
FormalMethodsVLSI.egg-info/dependency_links.txt
FormalMethodsVLSI.egg-info/requires.txt
FormalMethodsVLSI.egg-info/top_level.txt
Formal_methods/__init__.py
Formal_methods/approx_adder.py
Formal_methods/bdd.py
Formal_methods/nqueens.py
Formal_methods/BDD/BDD_from_netlist.py
Formal_methods/BDD/__init__.py
Formal_methods/BDD/cutnodes.py
Formal_methods/BDD/netlist.py
Formal_methods/SAT/__init__.py
Formal_methods/SAT/error_metrics.py
Formal_methods/SAT/error_miters.py
Formal_methods/SAT/sat_count.py